finalsa/sns/client/__init__.py
finalsa/sns/client/client/__init__.py
finalsa/sns/client/client/client.py
finalsa/sns/client/interface/__init__.py
finalsa/sns/client/interface/client.py
finalsa/sns/client/tests/__init__.py
finalsa/sns/client/tests/client.py
finalsa_sns_client-2.2.1.dist-info/METADATA
finalsa_sns_client-2.2.1.dist-info/WHEEL
finalsa_sns_client-2.2.1.dist-info/licenses/LICENSE.md
finalsa_sns_client-2.2.1.dist-info/RECORD
