Metadata-Version: 2.4
Name: finalsa-sns-client
Version: 2.2.1
Summary: Lightweight AWS SNS client for Python with topic management, subscriptions, and single/batch publishing with W3C trace headers.
Project-URL: Homepage, https://github.com/finalsa/sns-client
Author-email: Luis Jimenez <luis@finalsa.com>
License: MIT License
License-File: LICENSE.md
Keywords: aws,boto3,finalsa,messaging,pubsub,pydantic,sns,traceability
Requires-Python: >=3.10
Requires-Dist: boto3>=1.40.11
Requires-Dist: finalsa-common-models>=2.0.3
Requires-Dist: finalsa-traceability>=1.0.1
Requires-Dist: orjson>=3.11.2
